pureyak/__init__.py
pureyak/py.typed
pureyak-0.1.0rc1.dist-info/WHEEL
pureyak-0.1.0rc1.dist-info/METADATA
pureyak-0.1.0rc1.dist-info/RECORD
