Metadata-Version: 2.3
Name: pureyak
Version: 0.1.0rc1
Summary: 
Author: oyghen
Author-email: oyghen <oyghen@duck.com>
Requires-Python: >=3.11
